auto_rsync/__init__.py
auto_rsync-0.0.8.dist-info/METADATA
auto_rsync-0.0.8.dist-info/RECORD
auto_rsync-0.0.8.dist-info/WHEEL
auto_rsync-0.0.8.dist-info/entry_points.txt
auto_rsync-0.0.8.dist-info/top_level.txt
