Metadata-Version: 2.1
Name: auto-rsync
Version: 0.0.8
Summary: Auto RSync by watch filesystem events.
Home-page: http://github.com/yetone/auto-rsync
Author: yetone
Author-email: yetoneful@gmail.com
License: MIT License
Keywords: sync,rsync,auto rsync,auto,filesystem
Platform: UNKNOWN
Requires-Dist: click (==5.1)
Requires-Dist: watchdog (==0.8.3)
